README.md
setup.py
ett/__init__.py
ett/cuda.py
ett/pm.py
ett/random.py
ett/training.py
ett.egg-info/PKG-INFO
ett.egg-info/SOURCES.txt
ett.egg-info/dependency_links.txt
ett.egg-info/requires.txt
ett.egg-info/top_level.txt
ett.egg-info/zip-safe